fquery/__init__.py
fquery/aitertools.py
fquery/async_utils.py
fquery/execute.py
fquery/fgraphql.py
fquery/query.py
fquery/resolve.py
fquery/sql_builder.py
fquery/view_model.py
fquery/visitor.py
fquery/walk.py
tests/__init__.py
tests/async_test.py
tests/graphql_mock_user.py
tests/mock_user.py
tests/test_operators.py
tests/test_sql.py
tests/test_walk.py
tests/test_walk_obj.py
fquery-0.1.dist-info/LICENSE
fquery-0.1.dist-info/METADATA
fquery-0.1.dist-info/WHEEL
fquery-0.1.dist-info/top_level.txt
fquery-0.1.dist-info/RECORD
