Metadata-Version: 2.1
Name: fquery
Version: 0.1
Summary: A graph query engine
Home-page: UNKNOWN
License: UNKNOWN
Platform: UNKNOWN
Classifier: Programming Language :: Python :: 3
Classifier: License :: OSI Approved :: MIT License
Classifier: Operating System :: OS Independent
Requires-Python: >=3.6
Requires-Dist: aioitertools
Provides-Extra: sql
Requires-Dist: pypika (>=0.36.5) ; extra == 'sql'
Provides-Extra: graphql
Requires-Dist: strawberry (>=0.37.1) ; extra == 'graphql'
